CHANGES.txt
MANIFEST.in
README.rst
instructions.txt
requirements.txt
setup.cfg
setup.py
data/rpi2caster.conf
docs/instructions.txt
docs/rpi2caster.txt
rpi2caster/__init__.py
rpi2caster/__main__.py
rpi2caster/datatypes.py
rpi2caster/functions.py
rpi2caster/models.py
rpi2caster/monotype.py
rpi2caster/rpi2caster.py
rpi2caster/stats.py
rpi2caster/ui.py
rpi2caster.egg-info/PKG-INFO
rpi2caster.egg-info/SOURCES.txt
rpi2caster.egg-info/dependency_links.txt
rpi2caster.egg-info/entry_points.txt
rpi2caster.egg-info/requires.txt
rpi2caster.egg-info/top_level.txt
rpi2caster.egg-info/zip-safe
rpi2caster/data/__init__.py
rpi2caster/data/help.json
rpi2caster/data/wedge_units.json