Metadata-Version: 1.1
Name: rpi2caster
Version: 2.4.0
Summary: Machine control software for Monotype composition casters
Home-page: http://github.com/elegantandrogyne/rpi2caster
Author: Christophe Catherine Slychan
Author-email: krzysztof.slychan@gmail.com
License: GPLv3
Keywords: Monotype,typography,printing,letterpress,typesetting,typecasting,Raspberry Pi
Platform: UNKNOWN
Classifier: Development Status :: 4 - Beta
Classifier: Intended Audience :: Manufacturing
Classifier: License :: OSI Approved :: GNU General Public License v3 or later (GPLv3+)
Classifier: Natural Language :: English
Classifier: Operating System :: POSIX :: Linux
Classifier: Programming Language :: Python :: 3 :: Only
Classifier: Topic :: Artistic Software
